yai_loguru_sinks/__init__.py
yai_loguru_sinks/config.py
yai_loguru_sinks/py.typed
yai_loguru_sinks/internal/async_handler.py
yai_loguru_sinks/internal/core.py
yai_loguru_sinks/internal/data.py
yai_loguru_sinks/internal/factory.py
yai_loguru_sinks/internal/pack_id.py
yai_loguru_sinks/internal/protocol_parsers.py
yai_loguru_sinks/internal/sls_pack_id.py
yai_loguru_sinks/internal/url_parser.py
yai_loguru_sinks-0.6.3.dist-info/METADATA
yai_loguru_sinks-0.6.3.dist-info/WHEEL
yai_loguru_sinks-0.6.3.dist-info/RECORD
