Metadata-Version: 2.4
Name: yai-loguru-sinks
Version: 0.6.3
Summary: 企业级 Loguru Sink 工厂，基于 loguru-config 的简洁架构，专注于阿里云 SLS 支持
Project-URL: Homepage, https://github.com/your-org/yai-loguru-sinks
Project-URL: Repository, https://github.com/your-org/yai-loguru-sinks
Project-URL: Documentation, https://github.com/your-org/yai-loguru-sinks#readme
Project-URL: Issues, https://github.com/your-org/yai-loguru-sinks/issues
Author-email: Harry Tang <harry@example.com>
License: MIT
Keywords: aliyun,enterprise,logging,loguru,sink,sls
Classifier: Development Status :: 4 - Beta
Classifier: Intended Audience :: Developers
Classifier: License :: OSI Approved :: MIT License
Classifier: Programming Language :: Python :: 3
Classifier: Programming Language :: Python :: 3.10
Classifier: Programming Language :: Python :: 3.11
Classifier: Programming Language :: Python :: 3.12
Classifier: Programming Language :: Python :: 3.13
Classifier: Topic :: Software Development :: Libraries :: Python Modules
Classifier: Topic :: System :: Logging
Requires-Python: >=3.10
Requires-Dist: aliyun-log-python-sdk>=0.8.0
Requires-Dist: loguru-config>=0.1.0
Requires-Dist: loguru>=0.7.0
Requires-Dist: pydantic>=2.0.0
Requires-Dist: pytest>=8.3.5
Provides-Extra: dev
Requires-Dist: black>=23.0.0; extra == 'dev'
Requires-Dist: mypy>=1.0.0; extra == 'dev'
Requires-Dist: pytest-cov>=4.0.0; extra == 'dev'
Requires-Dist: pytest>=7.0.0; extra == 'dev'
Requires-Dist: ruff>=0.1.0; extra == 'dev'
